Workbook
Name CC_1: 'Contribution d''entretien'!$C$46
Name CC_2: 'Contribution d''entretien'!$D$46
Name man: 'Contribution d''entretien'!$F$45
Name nb_enfants: 'Contribution d''entretien'!$G$52
Name P_1: 'Contribution d''entretien'!$C$39
Name P_2: 'Contribution d''entretien'!$D$39

Sheet Contribution d'entretien
B2: Revenus
C4: Parent 1 | D4: Parent 2
B5: Revenus | C5: 5000 | D5: 4000
B6: Treizième salaire | C6: 0 | D6: 0
B7: Bonus annuel | C7: 0 | D7: 0
B8: Allocation(s) complémentaire(s) | C8: 0 | D8: 0
B9: Revenus complémentaires | C9: 0 | D9: 0
B10: TOTAL | C10: =SUM(C5*12+C6+C7)/12+SUM(C8:C9) -> 5000 | D10: =SUM(D5*12+D6+D7)/12+SUM(D8:D9) -> 4000
B12: Charges
B14: Montant de base | C14: 1200 | D14: 1350
B15: Part au loyer / intérêts hypothécaires | C15: 2500 | D15: 2000
B16: Coûts effectifs logement | C16: =IF(nb_enfants=0,C15,IF(P_1>=30%,IF(nb_enfants=1,C15*(1-Paramètres!$C8),IF(nb_enfants=2,(C15*(1-Paramètres!$D8)),IF(nb_enfants=3,(C15*(1-Paramètres!$E8)),C15*(1-Paramètres!$F8)))),C15)) -> 2500 | D16: =IF(nb_enfants=0,D15,IF(P_2>=30%,IF(nb_enfants=1,D15*(1-Paramètres!$C8),IF(nb_enfants=2,(D15*(1-Paramètres!$D8)),IF(nb_enfants=3,(D15*(1-Paramètres!$E8)),D15*(1-Paramètres!$F8)))),D15)) -> 2000
B17: Frais de chauffage | C17: 0 | D17: 0
B18: Frais accessoires | C18: 0 | D18: 0
B19: Prime LaMal/autres assurances obligatoires | C19: 545.95 | D19: 587.35
B20: Frais médicaux | D20: 0
B21: Frais de déplacement | C21: 284 | D21: 0
B22: Frais de repas | C22: 83 | D22: 0
B23: Leasing voiture si nécessaire | C23: 580.25 | D23: 385.95
B24: Autres charges
B25: TOTAL charges I | C25: =C14+SUM(C16:C24) -> 5193.2 | D25: =D14+SUM(D16:D24) -> 4323.3
B26: Impôts | C26: 1000 | D26: 200
B27: LCA | C27: 129 | D27: 160.7
B28: Autres assurances | C28: 31.4 | D28: 31
B29: Forfaits télécommunication | C29: 69 | D29: 78
B30: Caution loyer | C30: 17 | D30: 100
B31: Taxe déchets | C31: 0 | D31: 0
B32: 3ème pilier | C32: 250 | D32: 0
B33: Autres charges
B34: TOTAL charges I + II | C34: =SUM(C25:C33) -> 6689.6 | D34: =SUM(D25:D33) -> 4893
B37: Répartition garde
B39: % | C39: 0 | D39: =1-C39 -> 1
B41: Disponible
B43: Après déduction des charges I | C43: =C10-C25 -> -193.2 | D43: =D10-D25 -> -323.3
B44: Après déduction des charges I + II | C44: =C10-C34 -> -1689.6 | D44: =D10-D34 -> -893
B45: Disponible retenu | C45: =IF(man=1,C43,IF(man=2,C44,IF(OR($C44<0,$D44<0),C43,C44))) -> -193.2 | D45: =IF(man=1,D43,IF(man=2,D44,IF(OR($C44<0,$D44<0),D43,D44))) -> -323.3 | E45: Force manuellement disponible retenu 1 ou 2 | F45: 1 | G45: 0 ou vide:auto 1:dispo1 2:dispo2
B46: Pourcentage du disponible de la famille | C46: =IF(C45<=0,0,IF($C45*$D45>0,C45*100/($C45+$D45),100))/100 -> 0 | D46: =IF(D45<=0,0,IF($C45*$D45>0,D45*100/($C45+$D45),100))/100 -> 0
B47: Participation coûts directs enfants | C47: =IF(nb_enfants=0,0,SUM(C81:F81)) -> 0 | D47: =IF(nb_enfants=0,0,SUM(C82:F82)) -> 0
B48: Disponible après paiement des frais des enfants | C48: =C45-C47 -> -193.2 | D48: =D45-D47 -> -323.3 | E48: Si Disponible négatif du parent non-gardien, adapter les charges
C51: Frais des enfants | G51: Nombre enfants
B52: NOM | G52: =COUNTIF(C52:F52,"<>") -> 0
B53: Age enfants | C53: 14 | D53: 8 | E53: 12
B54: Charges
B55: Montant de base | C55: =IF(nb_enfants>0,IF(C53<10,400,600),0) -> 0 | D55: =IF(nb_enfants>1,IF(D53<10,400,600),0) -> 0 | E55: =IF(nb_enfants>2,IF(E53<10,400,600),0) -> 0 | F55: =IF(nb_enfants>3,IF(F53<10,400,600),0) -> 0
B56: Part au loyer parent 1 | C56: =IF(C39>=30%,IF(nb_enfants=0,0,IF(nb_enfants=1,($C$15*0.15),IF(nb_enfants=2,($C$15*0.15),$C$15*0.1))),0) -> 0 | D56: =IF(C39>=30%,IF(nb_enfants=0,0,IF(nb_enfants=1,0,IF(nb_enfants=2,($C$15*0.15),$C$15*0.1))),0) -> 0 | E56: =IF(C39>=30%,IF(nb_enfants=0,0,IF(nb_enfants=1,0,IF(nb_enfants=2,0,$C$15*0.1))),0) -> 0 | F56: =IF(C39>=30%,IF(nb_enfants<4,0,$C$15*0.1),0) -> 0
B57: Part au loyer parent 2 | C57: =IF(D39>=30%,IF(nb_enfants=0,0,IF(nb_enfants=1,(D$15*0.15),IF(nb_enfants=2,(D$15*0.15),D$15*0.1))),0) -> 0 | D57: =IF(D39>=30%,IF(nb_enfants=0,0,IF(nb_enfants=1,0,IF(nb_enfants=2,(D$15*0.15),D$15*0.1))),0) -> 0 | E57: =IF(D39>=30%,IF(nb_enfants=0,0,IF(nb_enfants=1,0,IF(nb_enfants=2,0,D$15*0.1))),0) -> 0 | F57: =IF(D39>=30%,IF(nb_enfants<4,0,D15*0.1),0) -> 0
B58: Assurance maladie | C58: 131.15 | D58: 131.15 | E58: 71.5 | F58: 0
B59: Assurance complémentaire | C59: 33.8 | D59: 32.6 | E59: 61 | F59: 0
B60: Frais médicaux | C60: 0 | D60: 0 | E60: 43.8
B61: Frais de formation | C61: 12.5 | D61: 0 | E61: 0 | F61: 0
B62: Frais de transports | C62: 22 | D62: 4.15 | E62: 2.5 | F62: 0
B63: Prise en charge tiers | C63: 0 | D63: 0 | E63: 0 | F63: 0
B64: Autres frais | C64: 66 | D64: 0
B65: Charges I | C65: =IF(nb_enfants=0,0,SUM(C55:C64)) -> 0 | D65: =IF(nb_enfants=0,0,SUM(D55:D64)) -> 0 | E65: =IF(nb_enfants=0,0,SUM(E55:E64)) -> 0 | F65: =IF(nb_enfants=0,0,SUM(F55:F64)) -> 0
B66: Impôts | C66: 0 | D66: 0 | E66: 50 | F66: 0
B67: Loisirs | C67: 200 | D67: 150 | E67: 50
B68: Assurance vie | D68: 0
B69: Télécommunication | C69: 0 | D69: 0 | E69: 41.95
B70: Epargne | C70: 0 | D70: 0
B71: Autres | C71: 0 | D71: 0 | E71: 0 | F71: 0
B72: Charges I+II | C72: =IF(nb_enfants>=1,SUM(C65:C71),0) -> 0 | D72: =IF(nb_enfants>=2,SUM(D65:D71),0) -> 0 | E72: =IF(nb_enfants>=3,SUM(E65:E71),0) -> 0 | F72: =IF(nb_enfants>=4,SUM(F65:F71),0) -> 0
B73: Allocations | C73: 275 | D73: 220 | E73: 220
B74: Autres revenus | C74: 0 | D74: 130 | E74: 130
B75: TOTAL Coûts directs | C75: =IF(nb_enfants=0,0,C72-C73-C74) -> 0 | D75: =IF(nb_enfants=0,0,D72-D73-D74) -> 0 | E75: =IF(nb_enfants=0,0,E72-E73-E74) -> 0 | F75: =IF(nb_enfants=0,0,F72-F73-F74) -> 0
B76: Coût assumable parent 1 | C76: =IF(nb_enfants=0,0,MAX(IF(SUM($C75:$E75)>$C45,IF(C52<>"",$C45/nb_enfants,0),C75),0)) -> 0 | D76: =IF(nb_enfants=0,0,MAX(IF(SUM($C75:$E75)>$C45,IF(D52<>"",$C45/nb_enfants,0),D75),0)) -> 0 | E76: =IF(nb_enfants=0,0,MAX(IF(SUM($C75:$E75)>$C45,IF(E52<>"",$C45/nb_enfants,0),E75),0)) -> 0 | F76: =IF(nb_enfants=0,0,MAX(IF(SUM($C75:$E75)>$C45,IF(F52<>"",$C45/nb_enfants,0),F75),0)) -> 0
B77: Coût assumable parent 2 | C77: =IF(nb_enfants=0,0,MAX(IF(SUM($C75:$E75)>$D45,IF(C52<>"",$D45/nb_enfants,0),C75),0)) -> 0 | D77: =IF(nb_enfants=0,0,MAX(IF(SUM($C75:$E75)>$D45,IF(D52<>"",$D45/nb_enfants,0),D75),0)) -> 0 | E77: =IF(nb_enfants=0,0,MAX(IF(SUM($C75:$E75)>$D45,IF(E52<>"",$D45/nb_enfants,0),E75),0)) -> 0 | F77: =IF(nb_enfants=0,0,MAX(IF(SUM($C75:$E75)>$D45,IF(F52<>"",$D45/nb_enfants,0),F75),0)) -> 0
B78: Contrib prise en charge en faveur parent 2 | C78: =IF(nb_enfants=0,0,IF(P_2>50%,IF(AND(D48<0,C48>0),MIN(-D48,C48),0),0)) -> 0
B79: Contrib prise en charge en faveur parent 1 | C79: =IF(nb_enfants=0,0,IF(P_1>50%,IF(AND(C48<0,D48>0),MIN(-C48,D48),0),0)) -> 0
B81: Participation parent 1 | C81: =IF(nb_enfants=0,0,MIN(IF(OR(P_2=0,CC_1=0),0,C$75*(CC_1*P_2)/(CC_2*P_1+CC_1*P_2)),C$76)) -> 0 | D81: =IF(nb_enfants=0,0,MIN(IF(OR(P_2=0,CC_1=0),0,D$75*(CC_1*P_2)/(CC_2*P_1+CC_1*P_2)),D$76)) -> 0 | E81: =IF(nb_enfants=0,0,MIN(IF(OR(P_2=0,CC_1=0),0,E$75*(CC_1*P_2)/(CC_2*P_1+CC_1*P_2)),E$76)) -> 0 | F81: =IF(nb_enfants=0,0,MIN(IF(OR(P_2=0,CC_1=0),0,F$75*(CC_1*P_2)/(CC_2*P_1+CC_1*P_2)),F$76)) -> 0
B82: Participation parent 2 | C82: =IF(nb_enfants=0,0,MIN(IF(OR(P_1=0,CC_2=0),0,C$75*(CC_2*P_1)/(CC_2*P_1+CC_1*P_2)),C$77)) -> 0 | D82: =IF(nb_enfants=0,0,MIN(IF(OR(P_1=0,CC_2=0),0,D$75*(CC_2*P_1)/(CC_2*P_1+CC_1*P_2)),D$77)) -> 0 | E82: =IF(nb_enfants=0,0,MIN(IF(OR(P_1=0,CC_2=0),0,E$75*(CC_2*P_1)/(CC_2*P_1+CC_1*P_2)),E$77)) -> 0 | F82: =IF(nb_enfants=0,0,MIN(IF(OR(P_1=0,CC_2=0),0,F$75*(CC_2*P_1)/(CC_2*P_1+CC_1*P_2)),F$77)) -> 0
B83: Participation dispo parent 1 | C83: =IF(nb_enfants>0,MAX((C$45-SUM(C76:F76)-C78)/(nb_enfants+4),0),0) -> 0 | D83: =IF(nb_enfants>1,MAX(($C$45-SUM($C76:F$76)-C78)/(nb_enfants+4),0),0) -> 0 | E83: =IF(nb_enfants>2,MAX(($C$45-SUM($C$76:F$76)-C78)/(nb_enfants+4),0),0) -> 0 | F83: =IF(nb_enfants>3,MAX(($C$45-SUM($C$76:$F$76)-C78)/(nb_enfants+4),0),0) -> 0 | G83: a vérifier ds garde alternée
B84: Participation dispo parent 2 | C84: =IF(nb_enfants>0,MAX(($D$45-SUM(C77:F77)-C79)/(nb_enfants+4),0),0) -> 0 | D84: =IF(nb_enfants>1,MAX(($D$45-SUM(C77:F77)-C79)/(nb_enfants+4),0),0) -> 0 | E84: =IF(nb_enfants>2,MAX(($D$45-SUM(C77:F77)-C79)/(nb_enfants+4),0),0) -> 0 | F84: =IF(nb_enfants>3,MAX(($D$45-SUM(C77:F77)-C79)/(nb_enfants+4),0),0) -> 0
B86: Total participation parent 1 | C86: =SUM(C81+C83) -> 0 | D86: =SUM(D81+D83) -> 0 | E86: =SUM(E81+E83) -> 0 | F86: =SUM(F81+F83) -> 0
B87: Total participation parent 2 | C87: =SUM(C82+C84) -> 0 | D87: =SUM(D82+D84) -> 0 | E87: =SUM(E82+E84) -> 0 | F87: =SUM(F82+F84) -> 0

Sheet Récapitulatif
B4: Parent 1 | C4: Parent 2
A5: TOTAL revenus | B5: ='Contribution d''entretien'!C10 -> 5000 | C5: ='Contribution d''entretien'!D10 -> 4000
A6: Charges | B6: ='Contribution d''entretien'!C34 -> 6689.6 | C6: ='Contribution d''entretien'!D34 -> 4893
A7: Couts direct | B7: ='Contribution d''entretien'!C47 -> 0 | C7: ='Contribution d''entretien'!D47 -> 0
A8: Participation dispo | B8: =SUM('Contribution d''entretien'!C83:E83) -> 0 | C8: =SUM('Contribution d''entretien'!C84:E84) -> 0
A11: Reste | B11: =B5-SUM(B6:B10) -> -1689.6 | C11: =C5-SUM(C6:C10) -> -893

Sheet Paramètres
A7: Nb enfants | B7: 0 | C7: 1 | D7: 2 | E7: 3 | F7: 4
A8: Part au loyer enfants | B8: 0 | C8: 0.15 | D8: 0.3 | E8: 0.35 | F8: 0.4
